{
    "prepare_queue": {
        "installed": [],
        "uninstalled": []
    },
    "config_munge": {
        "files": {}
    },
    "installed_plugins": {
        "cordova-plugin-whitelist": {
            "PACKAGE_NAME": "com.tmtvision.MobileApp"
        },
        "cordova-plugin-camera": {
            "PACKAGE_NAME": "com.tmtvision.MobileApp"
        },
        "cordova-plugin-compat": {
            "PACKAGE_NAME": "com.tmtvision.MobileApp"
        },
        "cordova-plugin-device-motion": {
            "PACKAGE_NAME": "com.tmtvision.MobileApp"
        },
        "cordova-plugin-file": {
            "PACKAGE_NAME": "com.tmtvision.MobileApp"
        }
    },
    "dependent_plugins": {}
}